mb/__init__.py
mb/__main__.py
mb/agent.py
mb/commands/jobs.py
mb/commands/keys.py
mb/commands/robots.py
mb/commands/tui.py
mb/crypto.py
mb/job_examples.py
mb/settings.py
mb/tui/object_info.tcss
mb/tui/tuiapp.py
rn_cli-0.2.4.dist-info/METADATA
rn_cli-0.2.4.dist-info/WHEEL
rn_cli-0.2.4.dist-info/entry_points.txt
rn_cli-0.2.4.dist-info/RECORD
