Metadata-Version: 2.1
Name: rn-cli
Version: 0.2.4
Summary: 
Author: alex
Author-email: alexander.smehnov@gmail.com
Requires-Python: >=3.8.1,<4.0.0
Classifier: Programming Language :: Python :: 3
Classifier: Programming Language :: Python :: 3.9
Classifier: Programming Language :: Python :: 3.10
Classifier: Programming Language :: Python :: 3.11
Classifier: Programming Language :: Python :: 3.12
Classifier: Programming Language :: Python :: 3.13
Requires-Dist: base58 (>=2.1.1,<3.0.0)
Requires-Dist: colorama (>=0.4.6,<0.5.0)
Requires-Dist: cryptography (>=43.0.0,<44.0.0)
Requires-Dist: pylint (>=3.2.6,<4.0.0)
Requires-Dist: pytest (>=8.0.0,<9.0.0)
Requires-Dist: python-socketio (>=5.11.3,<6.0.0)
Requires-Dist: pyyaml (>=6.0.2,<7.0.0)
Requires-Dist: readchar (>=4.1.0,<5.0.0)
Requires-Dist: requests (>=2.31.0,<3.0.0)
Requires-Dist: rich (>=13.7.0,<14.0.0)
Requires-Dist: shellingham (>=1.5.4,<2.0.0)
Requires-Dist: textual (>=0.75.1,<0.76.0)
Requires-Dist: typer (>=0.9.0,<0.10.0)
Requires-Dist: websockets (>=13.0,<14.0)
